MANIFEST.in
setup.py
rockspring/__init__.py
rockspring/generator.py
rockspring.egg-info/PKG-INFO
rockspring.egg-info/SOURCES.txt
rockspring.egg-info/dependency_links.txt
rockspring.egg-info/entry_points.txt
rockspring.egg-info/requires.txt
rockspring.egg-info/top_level.txt
rockspring/templates/client.pyx.jinja2
rockspring/templates/cpp_wrapper.pxd.jinja2
rockspring/templates/dto.h.jinja2
rockspring/templates/listener.cc.jinja2
rockspring/templates/listener.h.jinja2
rockspring/templates/services.h.jinja2
rockspring/templates/setup.py.jinja2